{
  "title": "Microservices SaaS App on Azure",
  "provider": "azure",
  "direction": "LR",
  "groups": [
    {
      "id": "vnet1",
      "label": "VNet",
      "parent": null
    },
    {
      "id": "subnet1",
      "label": "Application Subnet",
      "parent": "vnet1"
    },
    {
      "id": "subnet2",
      "label": "Data Subnet",
      "parent": "vnet1"
    }
  ],
  "nodes": [
    {
      "id": "user1",
      "type": "user",
      "label": "User",
      "group": null,
      "suggested_type": null,
      "suggestion_reason": null
    },
    {
      "id": "afd1",
      "type": "cdn",
      "label": "Azure Front Door",
      "group": null,
      "suggested_type": null,
      "suggestion_reason": null
    },
    {
      "id": "agw1",
      "type": "load_balancer",
      "label": "App Gateway WAF",
      "group": null,
      "suggested_type": null,
      "suggestion_reason": null
    },
    {
      "id": "containerapps1",
      "type": "compute.container",
      "label": "Container Apps",
      "group": "subnet1",
      "suggested_type": null,
      "suggestion_reason": null
    },
    {
      "id": "sql1",
      "type": "database.relational",
      "label": "Azure SQL Primary",
      "group": "subnet2",
      "suggested_type": null,
      "suggestion_reason": null
    },
    {
      "id": "sql2",
      "type": "database.relational",
      "label": "Azure SQL Failover",
      "group": "subnet2",
      "suggested_type": null,
      "suggestion_reason": null
    },
    {
      "id": "redis1",
      "type": "database.cache",
      "label": "Cache for Redis",
      "group": "subnet2",
      "suggested_type": null,
      "suggestion_reason": null
    },
    {
      "id": "servicebus1",
      "type": "queue",
      "label": "Service Bus",
      "group": null,
      "suggested_type": null,
      "suggestion_reason": null
    },
    {
      "id": "blob1",
      "type": "storage.object",
      "label": "Blob Storage",
      "group": null,
      "suggested_type": null,
      "suggestion_reason": null
    },
    {
      "id": "keyvault1",
      "type": "secrets",
      "label": "Key Vault",
      "group": null,
      "suggested_type": null,
      "suggestion_reason": null
    }
  ],
  "edges": [
    {
      "source": "user1",
      "target": "afd1",
      "label": "HTTPS",
      "style": "solid"
    },
    {
      "source": "afd1",
      "target": "agw1",
      "label": "HTTPS",
      "style": "solid"
    },
    {
      "source": "agw1",
      "target": "containerapps1",
      "label": "HTTPS",
      "style": "solid"
    },
    {
      "source": "containerapps1",
      "target": "sql1",
      "label": "SQL Queries",
      "style": "solid"
    },
    {
      "source": "sql1",
      "target": "sql2",
      "label": "Failover Replication",
      "style": "solid"
    },
    {
      "source": "containerapps1",
      "target": "redis1",
      "label": "Cache Access",
      "style": "solid"
    },
    {
      "source": "containerapps1",
      "target": "servicebus1",
      "label": "Messages",
      "style": "solid"
    },
    {
      "source": "containerapps1",
      "target": "blob1",
      "label": "File Storage",
      "style": "solid"
    },
    {
      "source": "containerapps1",
      "target": "keyvault1",
      "label": "Secrets Access",
      "style": "solid"
    }
  ],
  "show_legend": true
}